{
  "schema_version": 1,
  "pack_key": "sample-verification-pack",
  "version": "0.1.0",
  "status": "research",
  "owner": "TODO",
  "maintenance_owner": "TODO",
  "scope": {
    "migration_route": "java-to-csharp",
    "source_artifact_digest": "sha256:TODO",
    "target_artifact_digest": "sha256:TODO",
    "workload_key": "sample-workload",
    "risk_tier": "P0",
    "environment_digest": "sha256:TODO"
  },
  "contracts": {
    "validation_profile": "validation-profile.json",
    "oracle_registry": "oracle-registry.json",
    "assurance_case": "assurance/assurance-case.json"
  },
  "corpus": {
    "development": "corpus/development",
    "negative": "corpus/negative",
    "holdout": "corpus/holdout",
    "representative_workloads": "corpus/representative-workloads"
  },
  "certification": {
    "evidence_path": "certification/evidence.json",
    "result_path": "certification/gate-result.json"
  },
  "tags": [
    "advanced-verification"
  ]
}
